LICENSE
README.md
setup.py
makomailer/Exceptions.py
makomailer/FriendlyArgumentParser.py
makomailer/HelperClass.py
makomailer/MailsendGateway.py
makomailer/MakoMailer.py
makomailer/__init__.py
makomailer/__main__.py
makomailer.egg-info/PKG-INFO
makomailer.egg-info/SOURCES.txt
makomailer.egg-info/dependency_links.txt
makomailer.egg-info/entry_points.txt
makomailer.egg-info/requires.txt
makomailer.egg-info/top_level.txt