Metadata-Version: 2.1
Name: makomailer
Version: 0.0.3
Summary: Versatile CLI-based tool to send mails rendered from Mako templates, supporting SMTP and IMAP
Home-page: https://github.com/johndoe31415/makomailer
Download-URL: https://github.com/johndoe31415/makomailer/archive/v0.0.3.tar.gz
Author: Johannes Bauer
Author-email: joe@johannes-bauer.com
License: gpl-3.0
Keywords: mako,template,email
Classifier: Development Status :: 4 - Beta
Classifier: Intended Audience :: Developers
Classifier: License :: OSI Approved :: GNU General Public License v3 (GPLv3)
Classifier: Programming Language :: Python :: 3
Classifier: Programming Language :: Python :: 3 :: Only
Classifier: Programming Language :: Python :: 3.5
Classifier: Programming Language :: Python :: 3.6
Classifier: Programming Language :: Python :: 3.7
Classifier: Programming Language :: Python :: 3.8
Classifier: Programming Language :: Python :: 3.9
Classifier: Programming Language :: Python :: 3.10
License-File: LICENSE
Requires-Dist: mako
